preptools/__init__.py
preptools/__main__.py
preptools/exception.py
preptools/preptools_cli.py
preptools/version.py
preptools/command/__init__.py
preptools/command/bond_command.py
preptools/command/common_command.py
preptools/command/make_proposal_command.py
preptools/command/prep_info_command.py
preptools/command/prep_setting_command.py
preptools/command/proposal_info_command.py
preptools/command/proposal_setting_command.py
preptools/command/register_proposal2_command.py
preptools/command/tx_info_command.py
preptools/command/utils.py
preptools/command/make_proposal/__init__.py
preptools/command/make_proposal/accumulated_validation_failure_slashing_rate_command.py
preptools/command/make_proposal/call_method.py
preptools/command/make_proposal/command.py
preptools/command/make_proposal/malicious_score_command.py
preptools/command/make_proposal/missed_network_proposal_vote_slashing_rate_command.py
preptools/command/make_proposal/network_score_designation_command.py
preptools/command/make_proposal/network_score_update_command.py
preptools/command/make_proposal/prep_disqualification_command.py
preptools/command/make_proposal/revision_command.py
preptools/command/make_proposal/reward_fund_command.py
preptools/command/make_proposal/reward_funds_allocation_command.py
preptools/command/make_proposal/step_costs_command.py
preptools/command/make_proposal/step_price_command.py
preptools/command/make_proposal/text_command.py
preptools/core/__init__.py
preptools/core/prep.py
preptools/utils/__init__.py
preptools/utils/argparse_utils.py
preptools/utils/constants.py
preptools/utils/preptools_config.py
preptools/utils/utils.py
preptools/utils/validation_checker.py
preptools-1.3.2.dist-info/METADATA
preptools-1.3.2.dist-info/WHEEL
preptools-1.3.2.dist-info/entry_points.txt
preptools-1.3.2.dist-info/top_level.txt
preptools-1.3.2.dist-info/RECORD
