Metadata-Version: 2.1
Name: preptools
Version: 1.3.2
Summary: P-Rep management command line interface
Home-page: https://github.com/icon-project/preptools
Author: ICON Foundation
Author-email: foo@icon.foundation
License: Apache License 2.0
Platform: UNKNOWN
Classifier: Development Status :: 5 - Production/Stable
Classifier: Intended Audience :: Developers
Classifier: Intended Audience :: System Administrators
Classifier: Natural Language :: English
Classifier: License :: OSI Approved :: Apache Software License
Classifier: Programming Language :: Python :: 3
Classifier: Programming Language :: Python :: 3 :: Only
Classifier: Programming Language :: Python :: 3.7
Classifier: Programming Language :: Python :: 3.8
Classifier: Programming Language :: Python :: 3.9
Classifier: Programming Language :: Python :: 3.10
Classifier: Programming Language :: Python :: 3.11
Requires-Python: >=3.7
Requires-Dist: iconsdk >=2.3.0
Requires-Dist: iso3166 >=2.1.0
Provides-Extra: tests
Requires-Dist: pytest ~=6.2.5 ; extra == 'tests'
